pipeforge/__init__.py
pipeforge/__main__.py
pipeforge/_internal/__init__.py
pipeforge/_internal/core_loop.py
pipeforge/_internal/database.py
pipeforge/_internal/drawing.py
pipeforge/_internal/file_loader.py
pipeforge/_internal/inspector.py
pipeforge/_internal/params.py
pipeforge/_internal/pipeline.py
pipeforge/_internal/script.py
pipeforge/_internal/utils.py
pipeforge/examples/hello_jenkins.toml
pipeforge/examples/hello_world.toml
pipeforge/examples/merge_pull_request.toml
pipeforge/examples/multi_pipeline.toml
pipeforge/examples/multi_pipeline_2.toml
pipeforge/examples/nightly.toml
pipeforge/examples/retries.toml
pipeforge/examples/timeout.toml
pipeforge/examples/scripts/hello_world__get_purpose_in_life.py
pipeforge/examples/scripts/hello_world__print_summary.py
pipeforge/examples/scripts/hello_world__repeat_purpose.py
pipeforge/examples/scripts/retry.py
pipeforge/examples/scripts/timeout.py
pipeforge-1.2.0.dist-info/METADATA
pipeforge-1.2.0.dist-info/WHEEL
pipeforge-1.2.0.dist-info/entry_points.txt
pipeforge-1.2.0.dist-info/licenses/LICENSE
pipeforge-1.2.0.dist-info/RECORD
