Metadata-Version: 2.4
Name: pipeforge
Version: 1.2.0
Summary: A pipeline jobs orchestrator
Project-URL: Homepage, https://git.sr.ht/~greenfoo/pipeforge
Project-URL: Issues, https://todo.sr.ht/~greenfoo/pipeforge
License-File: LICENSE
Classifier: Operating System :: OS Independent
Classifier: Programming Language :: Python :: 3
Requires-Python: >=3.7
Requires-Dist: mongoengine
Requires-Dist: toml
Provides-Extra: jenkins
Requires-Dist: python-jenkins; extra == 'jenkins'
